{
  "pokemon-summary": [
    {
      "id": 1,
      "name": "Bulbasaur",
      "regnum": 1,
      "types": ["Grass", "Poison"],
      "height": "2'04''",
      "weight": "15.2",
      "img": "https://cdn.bulbagarden.net/upload/2/21/001Bulbasaur.png",
      "icon": "https://cdn.bulbagarden.net/upload/e/ec/001MS.png"
    },
    {
      "id": 2,
      "name": "Ivysaur",
      "regnum": 2,
      "types": ["Grass", "Poison"],
      "height": "3'03''",
      "weight": "28.7",
      "img": "https://cdn.bulbagarden.net/upload/7/73/002Ivysaur.png",
      "icon": "https://cdn.bulbagarden.net/upload/6/6b/002MS.png"
    },
    {
      "id": 3,
      "name": "Venusaur",
      "regnum": 3,
      "types": ["Grass", "Poison"],
      "height": "6'07''",
      "weight": "220.5",
      "img": "https://cdn.bulbagarden.net/upload/a/ae/003Venusaur.png",
      "icon": "https://cdn.bulbagarden.net/upload/d/df/003MS.png"
    },
    {
      "id": 4,
      "name": "Charmander",
      "regnum": 4,
      "types": ["Fire"],
      "height": "2'00''",
      "weight": "18.7",
      "img": "https://cdn.bulbagarden.net/upload/7/73/004Charmander.png",
      "icon": "https://cdn.bulbagarden.net/upload/b/bb/004MS.png"
    },
    {
      "id": 5,
      "name": "Charmeleon",
      "regnum": 5,
      "types": ["Fire"],
      "height": "3'07''",
      "weight": "41.9",
      "img": "https://cdn.bulbagarden.net/upload/4/4a/005Charmeleon.png",
      "icon": "https://cdn.bulbagarden.net/upload/d/dc/005MS.png"
    },
    {
      "id": 6,
      "name": "Charizard",
      "regnum": 6,
      "types": ["Fire", "Flying"],
      "height": "5'07'",
      "weight": "199.5",
      "img": "https://cdn.bulbagarden.net/upload/7/7e/006Charizard.png",
      "icon": "https://cdn.bulbagarden.net/upload/0/01/006MS.png"
    },
    {
      "id": 7,
      "name": "Squirtle",
      "regnum": 7,
      "types": ["Water"],
      "height": "1'08''",
      "weight": "19.8",
      "img": "https://cdn.bulbagarden.net/upload/3/39/007Squirtle.png",
      "icon": "https://cdn.bulbagarden.net/upload/9/92/007MS.png"
    },
    {
      "id": 8,
      "name": "Wartortle",
      "regnum": 8,
      "types": ["Water"],
      "height": "3'03''",
      "weight": "49.6",
      "img": "https://cdn.bulbagarden.net/upload/0/0c/008Wartortle.png",
      "icon": "https://cdn.bulbagarden.net/upload/f/f3/008MS.png"
    },
    {
      "id": 9,
      "name": "Blastoise",
      "regnum": 9,
      "types": ["Water"],
      "height": "5'03''",
      "weight": "188.5",
      "img": "https://cdn.bulbagarden.net/upload/0/02/009Blastoise.png",
      "icon": "https://cdn.bulbagarden.net/upload/c/cb/009MS.png"
    },
    {
      "id": 10,
      "name": "Caterpie",
      "regnum": 10,
      "types": ["Bug"],
      "height": "1'00''",
      "weight": "6.4",
      "img": "https://cdn.bulbagarden.net/upload/5/5d/010Caterpie.png",
      "icon": "https://cdn.bulbagarden.net/upload/6/69/010MS.png"
    },
    {
      "id": 11,
      "name": "Metapod",
      "regnum": 11,
      "types": ["Bug"],
      "height": "2'04''",
      "weight": "21.8",
      "img": "https://cdn.bulbagarden.net/upload/c/cd/011Metapod.png",
      "icon": "https://cdn.bulbagarden.net/upload/c/ce/011MS.png"
    },
    {
      "id": 12,
      "name": "Butterfree",
      "regnum": 12,
      "types": ["Bug", "Flying"],
      "height": "3'07''",
      "weight": "70.5",
      "img": "https://cdn.bulbagarden.net/upload/d/d1/012Butterfree.png",
      "icon": "https://cdn.bulbagarden.net/upload/1/14/012MS.png"
    },
    {
      "id": 13,
      "name": "Weedle",
      "regnum": 13,
      "types": ["Bug", "Poison"],
      "height": "1'00'",
      "weight": "7.1",
      "img": "https://cdn.bulbagarden.net/upload/d/df/013Weedle.png",
      "icon": "https://cdn.bulbagarden.net/upload/6/65/013MS.png"
    },
    {
      "id": 14,
      "name": "Kakuna",
      "regnum": 14,
      "types": ["Bug", "Poison"],
      "height": "2'00''",
      "weight": "22.0",
      "img": "https://cdn.bulbagarden.net/upload/f/f0/014Kakuna.png",
      "icon": "https://cdn.bulbagarden.net/upload/8/81/014MS.png"
    },
    {
      "id": 15,
      "name": "Beedrill",
      "regnum": 15,
      "types": ["Bug", "Poison"],
      "height": "3'03''",
      "weight": "65.0",
      "img": "https://cdn.bulbagarden.net/upload/6/61/015Beedrill.png",
      "icon": "https://cdn.bulbagarden.net/upload/5/5a/015MS.png"
    },
    {
      "id": 16,
      "name": "Pidgey",
      "regnum": 16,
      "types": ["Normal", "Flying"],
      "height": "1'00''",
      "weight": "4.0",
      "img": "https://cdn.bulbagarden.net/upload/5/55/016Pidgey.png",
      "icon": "https://cdn.bulbagarden.net/upload/9/9c/016MS.png"
    },
    {
      "id": 17,
      "name": "Pidgeotto",
      "regnum": 17,
      "types": ["Normal", "Flying"],
      "height": "3'07''",
      "weight": "66.1",
      "img": "https://cdn.bulbagarden.net/upload/7/7a/017Pidgeotto.png",
      "icon": "https://cdn.bulbagarden.net/upload/a/a9/017MS.png"
    },
    {
      "id": 18,
      "name": "Pidgeot",
      "regnum": 18,
      "types": ["Normal", "Flying"],
      "height": "4'11''",
      "weight": "87.1",
      "img": "https://cdn.bulbagarden.net/upload/5/57/018Pidgeot.png",
      "icon": "https://cdn.bulbagarden.net/upload/6/68/018MS.png"
    },
    {
      "id": 19,
      "name": "Rattata",
      "regnum": 19,
      "types": ["Normal"],
      "height": "1'00''",
      "weight": "7.7",
      "img": "https://cdn.bulbagarden.net/upload/4/46/019Rattata.png",
      "icon": "https://cdn.bulbagarden.net/upload/4/4d/019MS.png"
    },
    {
      "id": 20,
      "name": "Raticate",
      "regnum": 20,
      "types": ["Normal"],
      "height": "2'04''",
      "weight": "40.8",
      "img": "https://cdn.bulbagarden.net/upload/f/f4/020Raticate.png",
      "icon": "https://cdn.bulbagarden.net/upload/4/4d/020MS.png"
    },
    {
      "id": 21,
      "name": "Spearow",
      "regnum": 21,
      "types": ["Normal", "Flying"],
      "height": "1'00''",
      "weight": "4.4",
      "img": "https://cdn.bulbagarden.net/upload/8/8b/021Spearow.png",
      "icon": "https://cdn.bulbagarden.net/upload/5/5b/021MS.png"
    },
    {
      "id": 22,
      "name": "Fearow",
      "regnum": 22,
      "types": ["Normal", "Flying"],
      "height": "3'11''",
      "weight": "83.8",
      "img": "https://cdn.bulbagarden.net/upload/a/a0/022Fearow.png",
      "icon": "https://cdn.bulbagarden.net/upload/3/35/022MS.png"
    },
    {
      "id": 23,
      "name": "Ekans",
      "regnum": 23,
      "types": ["Poison"],
      "height": "6'07''",
      "weight": "15.2",
      "img": "https://cdn.bulbagarden.net/upload/f/fa/023Ekans.png",
      "icon": "https://cdn.bulbagarden.net/upload/0/0d/023MS.png"
    },
    {
      "id": 24,
      "name": "Arbok",
      "regnum": 24,
      "types": ["Poison"],
      "height": "11'06'",
      "weight": "143.3",
      "img": "https://cdn.bulbagarden.net/upload/c/cd/024Arbok.png",
      "icon": "https://cdn.bulbagarden.net/upload/d/d3/024MS.png"
    },
    {
      "id": 25,
      "name": "Pikachu",
      "regnum": 25,
      "types": ["Electric"],
      "height": "1'04''",
      "weight": "13.2",
      "img": "https://cdn.bulbagarden.net/upload/0/0d/025Pikachu.png",
      "icon": "https://cdn.bulbagarden.net/upload/0/0f/025MS.png"
    },
    {
      "id": 26,
      "name": "Raichu",
      "regnum": 26,
      "types": ["Electric"],
      "height": "2'07''",
      "weight": "66.1",
      "img": "https://cdn.bulbagarden.net/upload/8/88/026Raichu.png",
      "icon": "https://cdn.bulbagarden.net/upload/d/da/026MS.png"
    },
    {
      "id": 27,
      "name": "Sandshrew",
      "regnum": 27,
      "types": ["Ground"],
      "height": "2'00''",
      "weight": "26.5",
      "img": "https://cdn.bulbagarden.net/upload/9/9e/027Sandshrew.png",
      "icon": "https://cdn.bulbagarden.net/upload/c/c3/027MS.png"
    },
    {
      "id": 28,
      "name": "Sandslash",
      "regnum": 28,
      "types": ["Ground"],
      "height": "3'03''",
      "weight": "65.0",
      "img": "https://cdn.bulbagarden.net/upload/0/0b/028Sandslash.png",
      "icon": "https://cdn.bulbagarden.net/upload/e/e0/028MS.png"
    },
    {
      "id": 29,
      "name": "Nidoran♀",
      "regnum": 29,
      "types": ["Poison"],
      "height": "1'04''",
      "weight": "15.4",
      "img": "https://cdn.bulbagarden.net/upload/8/81/029Nidoran.png",
      "icon": "https://cdn.bulbagarden.net/upload/a/ab/029MS.png"
    },
    {
      "id": 30,
      "name": "Nidorina",
      "regnum": 30,
      "types": ["Poison"],
      "height": "2'07''",
      "weight": "44.1",
      "img": "https://cdn.bulbagarden.net/upload/c/cd/030Nidorina.png",
      "icon": "https://cdn.bulbagarden.net/upload/d/d0/030MS.png"
    },
    {
      "id": 31,
      "name": "Nidoqueen",
      "regnum": 31,
      "types": ["Poison", "Ground"],
      "height": "4'03''",
      "weight": "132.3",
      "img": "https://cdn.bulbagarden.net/upload/b/bf/031Nidoqueen.png",
      "icon": "https://cdn.bulbagarden.net/upload/3/31/031MS.png"
    },
    {
      "id": 32,
      "name": "Nidoran♂",
      "regnum": 32,
      "types": ["Poison"],
      "height": "1'08''",
      "weight": "19.8",
      "img": "https://cdn.bulbagarden.net/upload/4/4a/032Nidoran.png",
      "icon": "https://cdn.bulbagarden.net/upload/f/fb/032MS.png"
    },
    {
      "id": 33,
      "name": "Nidorina",
      "regnum": 33,
      "types": ["Poison"],
      "height": "2'11''",
      "weight": "43.0",
      "img": "https://cdn.bulbagarden.net/upload/9/9f/033Nidorino.png",
      "icon": "https://cdn.bulbagarden.net/upload/0/0e/033MS.png"
    },
    {
      "id": 34,
      "name": "Nidoking",
      "regnum": 34,
      "types": ["Poison", "Ground"],
      "height": "4'07''",
      "weight": "136.7",
      "img": "https://cdn.bulbagarden.net/upload/c/c6/034Nidoking.png",
      "icon": "https://cdn.bulbagarden.net/upload/1/18/034MS.png"
    },
    {
      "id": 35,
      "name": "Clefairy",
      "regnum": 35,
      "types": ["Normal"],
      "height": "2'00''",
      "weight": "16.5",
      "img": "https://cdn.bulbagarden.net/upload/f/f4/035Clefairy.png",
      "icon": "https://cdn.bulbagarden.net/upload/f/f9/035MS.png"
    },
    {
      "id": 36,
      "name": "Clefable",
      "regnum": 36,
      "types": ["Normal"],
      "height": "4'03''",
      "weight": "88.2",
      "img": "https://cdn.bulbagarden.net/upload/a/a9/036Clefable.png",
      "icon": "https://cdn.bulbagarden.net/upload/7/75/036MS.png"
    },
    {
      "id": 37,
      "name": "Vulpix",
      "regnum": 37,
      "types": ["Fire"],
      "height": "2'00''",
      "weight": "21.8",
      "img": "https://cdn.bulbagarden.net/upload/6/60/037Vulpix.png",
      "icon": "https://cdn.bulbagarden.net/upload/8/85/037MS.png"
    },
    {
      "id": 38,
      "name": "Ninetales",
      "regnum": 38,
      "types": ["Fire"],
      "height": "3'07''",
      "weight": "43.9",
      "img": "https://cdn.bulbagarden.net/upload/0/05/038Ninetales.png",
      "icon": "https://cdn.bulbagarden.net/upload/1/10/038MS.png"
    },
    {
      "id": 39,
      "name": "Jigglypuff",
      "regnum": 39,
      "types": ["Normal"],
      "height": "1'08''",
      "weight": "12.1",
      "img": "https://cdn.bulbagarden.net/upload/3/3e/039Jigglypuff.png",
      "icon": "https://cdn.bulbagarden.net/upload/9/9c/039MS.png"
    },
    {
      "id": 40,
      "name": "Wigglytuff",
      "regnum": 40,
      "types": ["Normal"],
      "height": "3'03''",
      "weight": "26.5",
      "img": "https://cdn.bulbagarden.net/upload/9/92/040Wigglytuff.png",
      "icon": "https://cdn.bulbagarden.net/upload/f/f1/040MS.png"
    },
    {
      "id": 41,
      "name": "Zubat",
      "regnum": 41,
      "types": ["Poison", "Flying"],
      "height": "2'07''",
      "weight": "16.5",
      "img": "https://cdn.bulbagarden.net/upload/d/da/041Zubat.png",
      "icon": "https://cdn.bulbagarden.net/upload/9/96/041MS.png"
    },
    {
      "id": 42,
      "name": "Golbat",
      "regnum": 42,
      "types": ["Poison", "Flying"],
      "height": "5'03''",
      "weight": "121.3",
      "img": "https://cdn.bulbagarden.net/upload/0/0c/042Golbat.png",
      "icon": "https://cdn.bulbagarden.net/upload/d/d0/042MS.png"
    },
    {
      "id": 43,
      "name": "Oddish",
      "regnum": 43,
      "types": ["Grass", "Poison"],
      "height": "1'08''",
      "weight": "11.9",
      "img": "https://cdn.bulbagarden.net/upload/4/43/043Oddish.png",
      "icon": "https://cdn.bulbagarden.net/upload/a/a5/043MS.png"
    },
    {
      "id": 44,
      "name": "Gloom",
      "regnum": 44,
      "types": ["Grass", "Poison"],
      "height": "2'07''",
      "weight": "19.0",
      "img": "https://cdn.bulbagarden.net/upload/2/2a/044Gloom.png",
      "icon": "https://cdn.bulbagarden.net/upload/d/d9/044MS.png"
    },
    {
      "id": 45,
      "name": "Vileplume",
      "regnum": 45,
      "types": ["Grass", "Poison"],
      "height": "3'11''",
      "weight": "41.0",
      "img": "https://cdn.bulbagarden.net/upload/6/6a/045Vileplume.png",
      "icon": "https://cdn.bulbagarden.net/upload/3/3e/045MS.png"
    },
    {
      "id": 46,
      "name": "Paras",
      "regnum": 46,
      "types": ["Bug", "Grass"],
      "height": "1'00''",
      "weight": "11.9",
      "img": "https://cdn.bulbagarden.net/upload/d/d4/046Paras.png",
      "icon": "https://cdn.bulbagarden.net/upload/7/7a/046MS.png"
    },
    {
      "id": 47,
      "name": "Parasect",
      "regnum": 47,
      "types": ["Bug", "Grass"],
      "height": "3'03''",
      "weight": "65.0",
      "img": "https://cdn.bulbagarden.net/upload/8/80/047Parasect.png",
      "icon": "https://cdn.bulbagarden.net/upload/4/41/047MS.png"
    },
    {
      "id": 48,
      "name": "Venonat",
      "regnum": 48,
      "types": ["Bug", "Poison"],
      "height": "3'03''",
      "weight": "66.1",
      "img": "https://cdn.bulbagarden.net/upload/a/ad/048Venonat.png",
      "icon": "https://cdn.bulbagarden.net/upload/1/1e/048MS.png"
    },
    {
      "id": 49,
      "name": "Venomoth",
      "regnum": 49,
      "types": ["Bug", "Poison"],
      "height": "4'11''",
      "weight": "27.6",
      "img": "https://cdn.bulbagarden.net/upload/d/d3/049Venomoth.png",
      "icon": "https://cdn.bulbagarden.net/upload/3/31/049MS.png"
    },
    {
      "id": 50,
      "name": "Diglett",
      "regnum": 50,
      "types": ["Ground"],
      "height": "0'08''",
      "weight": "1.8",
      "img": "https://cdn.bulbagarden.net/upload/3/31/050Diglett.png",
      "icon": "https://cdn.bulbagarden.net/upload/8/8b/050MS.png"
    },
    {
      "id": 51,
      "name": "Dugtrio",
      "regnum": 51,
      "types": ["Ground"],
      "height": "2'04''",
      "weight": "73.4",
      "img": "https://cdn.bulbagarden.net/upload/e/e5/051Dugtrio.png",
      "icon": "https://cdn.bulbagarden.net/upload/8/86/051MS.png"
    },
    {
      "id": 52,
      "name": "Meowth",
      "regnum": 52,
      "types": ["Normal"],
      "height": "1'04''",
      "weight": "9.3",
      "img": "https://cdn.bulbagarden.net/upload/d/d6/052Meowth.png",
      "icon": "https://cdn.bulbagarden.net/upload/5/50/052MS.png"
    },
    {
      "id": 53,
      "name": "Persian",
      "regnum": 53,
      "types": ["Normal"],
      "height": "3'03''",
      "weight": "70.5",
      "img": "https://cdn.bulbagarden.net/upload/1/13/053Persian.png",
      "icon": "https://cdn.bulbagarden.net/upload/a/a7/053MS.png"
    },
    {
      "id": 54,
      "name": "Psyduck",
      "regnum": 54,
      "types": ["Water"],
      "height": "2'07''",
      "weight": "43.2",
      "img": "https://cdn.bulbagarden.net/upload/5/53/054Psyduck.png",
      "icon": "https://cdn.bulbagarden.net/upload/6/6b/054MS.png"
    },
    {
      "id": 55,
      "name": "Golduck",
      "regnum": 55,
      "types": ["Water"],
      "height": "5'07''",
      "weight": "168.9",
      "img": "https://cdn.bulbagarden.net/upload/f/fe/055Golduck.png",
      "icon": "https://cdn.bulbagarden.net/upload/6/64/055MS.png"
    },
    {
      "id": 56,
      "name": "Mankey",
      "regnum": 56,
      "types": ["Fighting"],
      "height": "1'08''",
      "weight": "61.7",
      "img": "https://cdn.bulbagarden.net/upload/4/41/056Mankey.png",
      "icon": "https://cdn.bulbagarden.net/upload/a/ad/056MS.png"
    },
    {
      "id": 57,
      "name": "Primeape",
      "regnum": 57,
      "types": ["Fighting"],
      "height": "3'03''",
      "weight": "70.5",
      "img": "https://cdn.bulbagarden.net/upload/9/9a/057Primeape.png",
      "icon": "https://cdn.bulbagarden.net/upload/f/f1/057MS.png"
    },
    {
      "id": 58,
      "name": "Growlithe",
      "regnum": 58,
      "types": ["Fire"],
      "height": "2'04''",
      "weight": "41.9",
      "img": "https://cdn.bulbagarden.net/upload/3/3d/058Growlithe.png",
      "icon": "https://cdn.bulbagarden.net/upload/6/69/058MS.png"
    },
    {
      "id": 59,
      "name": "Arcanine",
      "regnum": 59,
      "types": ["Fire"],
      "height": "6'03''",
      "weight": "341.7",
      "img": "https://cdn.bulbagarden.net/upload/b/b8/059Arcanine.png",
      "icon": "https://cdn.bulbagarden.net/upload/3/35/059MS.png"
    },
    {
      "id": 60,
      "name": "Poliwag",
      "regnum": 60,
      "types": ["Water"],
      "height": "2'00''",
      "weight": "27.3",
      "img": "https://cdn.bulbagarden.net/upload/4/49/060Poliwag.png",
      "icon": "https://cdn.bulbagarden.net/upload/1/17/060MS.png"
    },
    {
      "id": 61,
      "name": "Poliwhirl",
      "regnum": 61,
      "types": ["Water"],
      "height": "3'03''",
      "weight": "44.1",
      "img": "https://cdn.bulbagarden.net/upload/a/a9/061Poliwhirl.png",
      "icon": "https://cdn.bulbagarden.net/upload/3/36/061MS.png"
    },
    {
      "id": 62,
      "name": "Poliwrath",
      "regnum": 62,
      "types": ["Water", "Fighting"],
      "height": "4'03''",
      "weight": "119.0",
      "img": "https://cdn.bulbagarden.net/upload/2/2d/062Poliwrath.png",
      "icon": "https://cdn.bulbagarden.net/upload/5/5e/062MS.png"
    },
    {
      "id": 63,
      "name": "Abra",
      "regnum": 63,
      "types": ["Psychic"],
      "height": "2'11''",
      "weight": "43.0",
      "img": "https://cdn.bulbagarden.net/upload/6/62/063Abra.png",
      "icon": "https://cdn.bulbagarden.net/upload/c/cf/063MS.png"
    },
    {
      "id": 64,
      "name": "Kadabra",
      "regnum": 64,
      "types": ["Psychic"],
      "height": "4'03''",
      "weight": "124.6",
      "img": "https://cdn.bulbagarden.net/upload/9/97/064Kadabra.png",
      "icon": "https://cdn.bulbagarden.net/upload/b/b6/064MS.png"
    },
    {
      "id": 65,
      "name": "Alakazam",
      "regnum": 65,
      "types": ["Psychic"],
      "height": "4'11''",
      "weight": "105.8",
      "img": "https://cdn.bulbagarden.net/upload/c/cc/065Alakazam.png",
      "icon": "https://cdn.bulbagarden.net/upload/c/ca/065MS.png"
    },
    {
      "id": 66,
      "name": "Machop",
      "regnum": 66,
      "types": ["Fighting"],
      "height": "2'07''",
      "weight": "43.0",
      "img": "https://cdn.bulbagarden.net/upload/8/85/066Machop.png",
      "icon": "https://cdn.bulbagarden.net/upload/6/6c/066MS.png"
    },
    {
      "id": 67,
      "name": "Machoke",
      "regnum": 67,
      "types": ["Fighting"],
      "height": "4'11''",
      "weight": "155.4",
      "img": "https://cdn.bulbagarden.net/upload/8/8e/067Machoke.png",
      "icon": "https://cdn.bulbagarden.net/upload/0/0f/067MS.png"
    },
    {
      "id": 68,
      "name": "Machamp",
      "regnum": 68,
      "types": ["Fighting"],
      "height": "5'03''",
      "weight": "286.6",
      "img": "https://cdn.bulbagarden.net/upload/8/8f/068Machamp.png",
      "icon": "https://cdn.bulbagarden.net/upload/1/1e/068MS.png"
    },
    {
      "id": 69,
      "name": "Bellsprout",
      "regnum": 69,
      "types": ["Grass", "Poison"],
      "height": "2'04''",
      "weight": "8.8",
      "img": "https://cdn.bulbagarden.net/upload/a/a2/069Bellsprout.png",
      "icon": "https://cdn.bulbagarden.net/upload/7/7b/069MS.png"
    },
    {
      "id": 70,
      "name": "Weepinbell",
      "regnum": 70,
      "types": ["Grass", "Poison"],
      "height": "3'03''",
      "weight": "14.1",
      "img": "https://cdn.bulbagarden.net/upload/9/9f/070Weepinbell.png",
      "icon": "https://cdn.bulbagarden.net/upload/d/d5/070MS.png"
    },
    {
      "id": 71,
      "name": "Victreebel",
      "regnum": 71,
      "types": ["Grass", "Poison"],
      "height": "5'07''",
      "weight": "34.2",
      "img": "https://cdn.bulbagarden.net/upload/b/be/071Victreebel.png",
      "icon": "https://cdn.bulbagarden.net/upload/9/9b/071MS.png"
    },
    {
      "id": 72,
      "name": "Tentacool",
      "regnum": 72,
      "types": ["Water", "Poison"],
      "height": "2'11''",
      "weight": "100.3",
      "img": "https://cdn.bulbagarden.net/upload/4/4e/072Tentacool.png",
      "icon": "https://cdn.bulbagarden.net/upload/4/42/072MS.png"
    },
    {
      "id": 73,
      "name": "Tentacruel",
      "regnum": 73,
      "types": ["Water", "Poison"],
      "height": "5'03''",
      "weight": "121.3",
      "img": "https://cdn.bulbagarden.net/upload/f/f6/073Tentacruel.png",
      "icon": "https://cdn.bulbagarden.net/upload/f/fc/073MS.png"
    },
    {
      "id": 74,
      "name": "Geodude",
      "regnum": 74,
      "types": ["Rock", "Ground"],
      "height": "1'04''",
      "weight": "44.1",
      "img": "https://cdn.bulbagarden.net/upload/9/98/074Geodude.png",
      "icon": "https://cdn.bulbagarden.net/upload/0/04/074MS.png"
    },
    {
      "id": 75,
      "name": "Graveler",
      "regnum": 75,
      "types": ["Rock", "Ground"],
      "height": "3'03''",
      "weight": "231.5",
      "img": "https://cdn.bulbagarden.net/upload/7/75/075Graveler.png",
      "icon": "https://cdn.bulbagarden.net/upload/5/5c/075MS.png"
    },
    {
      "id": 76,
      "name": "Golem",
      "regnum": 76,
      "types": ["Rock", "Ground"],
      "height": "4'07''",
      "weight": "661.4",
      "img": "https://cdn.bulbagarden.net/upload/f/f2/076Golem.png",
      "icon": "https://cdn.bulbagarden.net/upload/3/34/076MS.png"
    },
    {
      "id": 77,
      "name": "Ponyta",
      "regnum": 77,
      "types": ["Fire"],
      "height": "3'03''",
      "weight": "66.1",
      "img": "https://cdn.bulbagarden.net/upload/3/3b/077Ponyta.png",
      "icon": "https://cdn.bulbagarden.net/upload/5/55/077MS.png"
    },
    {
      "id": 78,
      "name": "Rapidash",
      "regnum": 78,
      "types": ["Fire"],
      "height": "5'07''",
      "weight": "209.4",
      "img": "https://cdn.bulbagarden.net/upload/3/3f/078Rapidash.png",
      "icon": "https://cdn.bulbagarden.net/upload/6/66/078MS.png"
    },
    {
      "id": 79,
      "name": "Slowpoke",
      "regnum": 78,
      "types": ["Water", "Psychic"],
      "height": "3'11''",
      "weight": "79.4",
      "img": "https://cdn.bulbagarden.net/upload/7/70/079Slowpoke.png",
      "icon": "https://cdn.bulbagarden.net/upload/6/6a/079MS.png"
    },
    {
      "id": 80,
      "name": "Slowbro",
      "regnum": 80,
      "types": ["Water", "Psychic"],
      "height": "5'03''",
      "weight": "173.1",
      "img": "https://cdn.bulbagarden.net/upload/8/80/080Slowbro.png",
      "icon": "https://cdn.bulbagarden.net/upload/b/b6/080MS.png"
    },
    {
      "id": 81,
      "name": "Magnemite",
      "regnum": 81,
      "types": ["Electric", "Steel"],
      "height": "1'00''",
      "weight": "13.2",
      "img": "https://cdn.bulbagarden.net/upload/6/6c/081Magnemite.png",
      "icon": "https://cdn.bulbagarden.net/upload/0/0f/081MS.png"
    },
    {
      "id": 82,
      "name": "Magneton",
      "regnum": 82,
      "types": ["Electric", "Steel"],
      "height": "3'03''",
      "weight": "132.3",
      "img": "https://cdn.bulbagarden.net/upload/7/72/082Magneton.png",
      "icon": "https://cdn.bulbagarden.net/upload/0/0c/082MS.png"
    },
    {
      "id": 83,
      "name": "Farfetch'd",
      "regnum": 83,
      "types": ["Normal", "Flying"],
      "height": "2'07''",
      "weight": "33.1",
      "img": "https://cdn.bulbagarden.net/upload/f/f8/083Farfetch%27d.png",
      "icon": "https://cdn.bulbagarden.net/upload/5/57/083MS.png"
    }
  ]
}